fastclone/__init__.py
fastclone/__main__.py
fastclone/loaders.py
fastclone/phylogeny.py
fastclone/subclone.py
fastclone_guanlab-1.0.9.dist-info/LICENSE.txt
fastclone_guanlab-1.0.9.dist-info/METADATA
fastclone_guanlab-1.0.9.dist-info/WHEEL
fastclone_guanlab-1.0.9.dist-info/entry_points.txt
fastclone_guanlab-1.0.9.dist-info/top_level.txt
fastclone_guanlab-1.0.9.dist-info/RECORD
