Metadata-Version: 2.1
Name: fastclone-guanlab
Version: 1.0.9
Summary: An inference tool for tumour subclonal composition
Home-page: http://github.com/GuanLab/FastClone_GuanLab
Author: Hongjiu Zhang, Yuanfang Guan, Yao Xiao
Author-email: zhanghj@umich.edu, gyuanfan@umich.edu, yxiaoy@umich.edu
License: GPLv3+
Keywords: bioinformatics
Platform: UNKNOWN
Classifier: Development Status :: 3 - Alpha
Classifier: Environment :: Console
Classifier: Intended Audience :: Developers
Classifier: Intended Audience :: Science/Research
Classifier: License :: OSI Approved :: GNU General Public License v3 or later (GPLv3+)
Classifier: Natural Language :: English
Classifier: Operating System :: OS Independent
Classifier: Programming Language :: Python
Classifier: Programming Language :: Python :: 3 :: Only
Classifier: Programming Language :: Python :: 3
Classifier: Programming Language :: Python :: 3.5
Classifier: Programming Language :: Python :: 3.6
Classifier: Programming Language :: Python :: 3.7
Classifier: Topic :: Scientific/Engineering :: Bio-Informatics
Requires-Python: >=3.5.0
License-File: LICENSE.txt
Requires-Dist: logbook
Requires-Dist: pandas
Requires-Dist: scikit-learn
Requires-Dist: fire
Requires-Dist: networkx
Requires-Dist: matplotlib
